floodr-0.1.0.dist-info/METADATA
floodr-0.1.0.dist-info/WHEEL
floodr-0.1.0.dist-info/licenses/LICENSE
floodr/__init__.py
floodr/benchmark.py
floodr/floodr.abi3.so
floodr/models.py
floodr-0.1.0.dist-info/RECORD
