Metadata-Version: 2.4
Name: floodr
Version: 0.1.0
Classifier: Development Status :: 4 - Beta
Classifier: Intended Audience :: Developers
Classifier: License :: OSI Approved :: MIT License
Classifier: Programming Language :: Python :: Implementation :: CPython
Classifier: Programming Language :: Python :: 3
Classifier: Programming Language :: Python :: 3.9
Classifier: Programming Language :: Python :: 3.10
Classifier: Programming Language :: Python :: 3.11
Classifier: Programming Language :: Python :: 3.12
Classifier: Programming Language :: Rust
Classifier: Topic :: Internet :: WWW/HTTP
Classifier: Topic :: Software Development :: Libraries :: Python Modules
Classifier: Typing :: Typed
Classifier: Operating System :: OS Independent
Requires-Dist: pydantic>=2.0.0
Requires-Dist: pytest>=7.0.0 ; extra == 'dev'
Requires-Dist: pytest-asyncio>=0.21.0 ; extra == 'dev'
Requires-Dist: httpx>=0.24.0 ; extra == 'dev'
Requires-Dist: black>=23.0.0 ; extra == 'dev'
Requires-Dist: ruff>=0.1.0 ; extra == 'dev'
Requires-Dist: mypy>=1.0.0 ; extra == 'dev'
Requires-Dist: maturin>=1.0.0 ; extra == 'dev'
Provides-Extra: dev
License-File: LICENSE
Summary: Fast parallel HTTP requests for Python, powered by Rust
Keywords: http,requests,async,parallel,rust,performance,client
Author-email: floodr contributors <>
License: MIT
Requires-Python: >=3.9
Project-URL: Homepage, https://github.com/cemoody/floodr
Project-URL: Documentation, https://github.com/cemoody/floodr#readme
Project-URL: Repository, https://github.com/cemoody/floodr
Project-URL: Issues, https://github.com/cemoody/floodr/issues
